{
  "project_info": {
    "project_number": "763272425222",
    "project_id": "instasaver-android",
    "storage_bucket": "instasaver-android.firebasestorage.app"
  },
  "client": [
    {
      "client_info": {
        "mobilesdk_app_id": "1:763272425222:android:3f2e47a8127d0da3ed7887",
        "android_client_info": {
          "package_name": "com.video.downloader.saver.manager.free.allvideodownloader"
        }
      },
      "oauth_client": [],
      "api_key": [
        {
          "current_key": "AIzaSyCtEHh110-eSp-sjHqdzXcExX34zTLBjhM"
        }
      ],
      "services": {
        "appinvite_service": {
          "other_platform_oauth_client": []
        }
      }
    }
  ],
  "configuration_version": "1"
}